fava/__init__.py
fava/_ctx_globals_class.py
fava/application.py
fava/cli.py
fava/context.py
fava/helpers.py
fava/internal_api.py
fava/json_api.py
fava/py.typed
fava/serialisation.py
fava/template_filters.py
fava/beans/__init__.py
fava/beans/abc.py
fava/beans/account.py
fava/beans/create.py
fava/beans/flags.py
fava/beans/funcs.py
fava/beans/helpers.py
fava/beans/ingest.py
fava/beans/load.py
fava/beans/prices.py
fava/beans/protocols.py
fava/beans/str.py
fava/beans/types.py
fava/core/__init__.py
fava/core/accounts.py
fava/core/attributes.py
fava/core/budgets.py
fava/core/charts.py
fava/core/commodities.py
fava/core/conversion.py
fava/core/documents.py
fava/core/extensions.py
fava/core/fava_options.py
fava/core/file.py
fava/core/filters.py
fava/core/group_entries.py
fava/core/ingest.py
fava/core/inventory.py
fava/core/misc.py
fava/core/module_base.py
fava/core/number.py
fava/core/query.py
fava/core/query_shell.py
fava/core/tree.py
fava/core/watcher.py
fava/ext/__init__.py
fava/ext/auto_commit.py
fava/ext/fava_ext_test/FavaExtTest.js
fava/ext/fava_ext_test/__init__.py
fava/ext/fava_ext_test/templates/FavaExtTest.html
fava/ext/fava_ext_test/templates/FavaExtTestInclude.html
fava/ext/portfolio_list/PortfolioList.js
fava/ext/portfolio_list/__init__.py
fava/ext/portfolio_list/templates/PortfolioList.html
fava/help/__init__.py
fava/help/_index.md
fava/help/beancount_syntax.md
fava/help/budgets.md
fava/help/conversion.md
fava/help/extensions.md
fava/help/features.md
fava/help/filters.md
fava/help/import.md
fava/help/options.md
fava/plugins/__init__.py
fava/plugins/link_documents.py
fava/plugins/tag_discovered_documents.py
fava/static/app.css
fava/static/app.css.map
fava/static/app.js
fava/static/app.js.map
fava/static/beancount-LDUJ2SQ5.js
fava/static/beancount-LDUJ2SQ5.js.map
fava/static/beancount-MGPVJVZT.css
fava/static/beancount-MGPVJVZT.css.map
fava/static/bql-MGFRUMBP.js
fava/static/bql-MGFRUMBP.js.map
fava/static/chunk-E7ZF4ASL.js
fava/static/chunk-E7ZF4ASL.js.map
fava-1.30.11.dist-info/licenses/AUTHORS
fava-1.30.11.dist-info/licenses/LICENSE
fava-1.30.11.dist-info/METADATA
fava-1.30.11.dist-info/WHEEL
fava-1.30.11.dist-info/entry_points.txt
fava-1.30.11.dist-info/top_level.txt
fava-1.30.11.dist-info/RECORD
