Metadata-Version: 2.4
Name: fava
Version: 1.30.11
Summary: Web interface for the accounting tool Beancount.
Author-email: Dominik Aumayr <dominik@aumayr.name>
Maintainer-email: Jakob Schnitzer <mail@jakobschnitzer.de>
License-Expression: MIT
Project-URL: Homepage, https://beancount.github.io/fava/
Project-URL: Changelog, https://beancount.github.io/fava/changelog.html
Project-URL: Source, https://github.com/beancount/fava/
Project-URL: Issues, https://github.com/beancount/fava/issues/
Project-URL: Chat, https://gitter.im/beancount/fava
Keywords: fava,beancount,accounting
Classifier: Development Status :: 5 - Production/Stable
Classifier: Environment :: Web Environment
Classifier: Framework :: Flask
Classifier: Intended Audience :: Education
Classifier: Intended Audience :: End Users/Desktop
Classifier: Intended Audience :: Financial and Insurance Industry
Classifier: Intended Audience :: Information Technology
Classifier: Natural Language :: English
Classifier: Programming Language :: JavaScript
Classifier: Programming Language :: Python :: 3 :: Only
Classifier: Programming Language :: Python :: 3.10
Classifier: Programming Language :: Python :: 3.11
Classifier: Programming Language :: Python :: 3.12
Classifier: Programming Language :: Python :: 3.13
Classifier: Programming Language :: Python :: 3.14
Classifier: Topic :: Internet :: WWW/HTTP :: Dynamic Content
Classifier: Topic :: Office/Business :: Financial :: Accounting
Classifier: Topic :: Office/Business :: Financial :: Investment
Requires-Python: >=3.10
License-File: LICENSE
License-File: AUTHORS
Requires-Dist: Babel<3,>=2.11
Requires-Dist: Flask-Babel<5,>=3
Requires-Dist: Flask<4,>=2.2
Requires-Dist: Jinja2<4,>=3
Requires-Dist: Werkzeug<4,>=2.2
Requires-Dist: beancount<4,>=2
Requires-Dist: beanquery<0.3,>=0.1
Requires-Dist: beangulp>=0.1
Requires-Dist: cheroot<12,>=8
Requires-Dist: click<9,>=7
Requires-Dist: markdown2<3,>=2.3.0
Requires-Dist: ply>=3.4
Requires-Dist: simplejson<4,>=3.16.0
Requires-Dist: watchfiles>=0.20.0
Requires-Dist: typing-extensions>=4.5; python_version < "3.12"
Provides-Extra: excel
Requires-Dist: pyexcel>=0.5; extra == "excel"
Requires-Dist: pyexcel-ods3>=0.5; extra == "excel"
Requires-Dist: pyexcel-xlsx>=0.5; extra == "excel"
Dynamic: license-file
